gtd/__init__.py
gtd/__main__.py
gtd/main.py
gtd-0.0.4.dist-info/DESCRIPTION.rst
gtd-0.0.4.dist-info/METADATA
gtd-0.0.4.dist-info/RECORD
gtd-0.0.4.dist-info/WHEEL
gtd-0.0.4.dist-info/entry_points.txt
gtd-0.0.4.dist-info/metadata.json
gtd-0.0.4.dist-info/top_level.txt
tab/__init__.py
tab/__main__.py
tab/main.py
