Metadata-Version: 2.0
Name: gtd
Version: 0.0.4
Summary: Manages a simple log book, to Get Things Done
Home-page: https://github.com/magmax/logbook
Author: Miguel Ángel García
Author-email: miguelangel.garcia@gmail.com
License: MIT
Keywords: logbook scheduler todo backlog
Platform: UNKNOWN
Classifier: Development Status :: 3 - Alpha
Classifier: Programming Language :: Python :: 3.4
Classifier: Programming Language :: Python :: 3.5
Classifier: Programming Language :: Python :: 3.6
Classifier: Programming Language :: Python :: Implementation :: CPython
Classifier: License :: OSI Approved :: MIT License
Classifier: Topic :: Software Development :: Documentation
Classifier: Operating System :: OS Independent
Requires-Dist: pyyaml
Provides-Extra: develop
Requires-Dist: coveralls (>=1.1); extra == 'develop'
Requires-Dist: flake8 (>=3.3.8); extra == 'develop'
Requires-Dist: pytest (>=3.0.6); extra == 'develop'
Requires-Dist: pytest-cov (>=2.4.0); extra == 'develop'
